README.rst
setup.py
mlak/DataIO.py
mlak/FeatureTools.py
mlak/KerasSolver.py
mlak/LinearAlgebra.py
mlak/LinearRegression.py
mlak/Logger.py
mlak/LogisticRegression.py
mlak/MathTools.py
mlak/ModelAnalyzer.py
mlak/ModelsBase.py
mlak/NeuralNetwork.py
mlak/OptimizationAlgorithms.py
mlak/Terminal.py
mlak/Visual.py
mlak/__init__.py
mlak/mlak.py
mlak.egg-info/PKG-INFO
mlak.egg-info/SOURCES.txt
mlak.egg-info/dependency_links.txt
mlak.egg-info/entry_points.txt
mlak.egg-info/requires.txt
mlak.egg-info/top_level.txt