Metadata-Version: 1.1
Name: mlak
Version: 0.0.0
Summary: Machine Learning Army Knife
Home-page: https://github.com/codestation-org/mlak
Author: Marcin `amok` Konarski
Author-email: amok@codestation.org
License: Python Software Foundation License
Keywords: machine learning keras neural network neuronal logistic regression linear model analyzer
Platform: UNKNOWN
Classifier: Environment :: Console
Classifier: Development Status :: 3 - Alpha
Classifier: Intended Audience :: Science/Research
Classifier: Topic :: Scientific/Engineering :: Artificial Intelligence
Classifier: License :: OSI Approved :: Python Software Foundation License
Classifier: Programming Language :: Python :: 3
